geezpy/__init__.py
geezpy/__main__.py
geezpy/keywords.json
geezpy/translator.py
geezpy-0.1.0.dist-info/METADATA
geezpy-0.1.0.dist-info/WHEEL
geezpy-0.1.0.dist-info/entry_points.txt
geezpy-0.1.0.dist-info/top_level.txt
geezpy-0.1.0.dist-info/RECORD
