Metadata-Version: 2.4
Name: geezpy
Version: 0.1.0
Summary: A Python library to enable coding with Amharic keywords.
Home-page: https://github.com/yourusername/geezpy
Author: Yonathan Yitagesu
Author-email: yonathanyitagesuaklilu@gmail.com
Classifier: Programming Language :: Python :: 3
Classifier: License :: OSI Approved :: MIT License
Classifier: Operating System :: OS Independent
Classifier: Development Status :: 3 - Alpha
Classifier: Intended Audience :: Developers
Classifier: Topic :: Software Development :: Compilers
Classifier: Topic :: Software Development :: Interpreters
Classifier: Topic :: Software Development :: Localization
Requires-Python: >=3.8
Dynamic: author
Dynamic: author-email
Dynamic: classifier
Dynamic: description
Dynamic: description-content-type
Dynamic: home-page
Dynamic: requires-python
Dynamic: summary
